pipeteer/__init__.py
pipeteer/__init__.pyi
pipeteer/backend/__init__.py
pipeteer/backend/__init__.pyi
pipeteer/backend/db.py
pipeteer/backend/zmq.py
pipeteer/cli/__init__.py
pipeteer/cli/__init__.pyi
pipeteer/cli/cli.py
pipeteer/pipelines/__init__.py
pipeteer/pipelines/__init__.pyi
pipeteer/pipelines/_activity.py
pipeteer/pipelines/_multitask.py
pipeteer/pipelines/_task.py
pipeteer/pipelines/_workflow.py
pipeteer/pipelines/pipeline.py
pipeteer/util/__init__.py
pipeteer/util/__init__.pyi
pipeteer/util/asyn.py
pipeteer/util/types.py
pipeteer-1.0.5.dist-info/METADATA
pipeteer-1.0.5.dist-info/WHEEL
pipeteer-1.0.5.dist-info/entry_points.txt
pipeteer-1.0.5.dist-info/top_level.txt
pipeteer-1.0.5.dist-info/RECORD
